{
  "marks": [
    {
      "type": "rect",
      "from": {
        "data": "table"
      },
      "encode": {
        "enter": {
          "x": {
            "scale": "xscale",
            "field": "category"
          },
          "width": {
            "scale": "xscale",
            "band": 1
          },
          "y": {
            "scale": "yscale",
            "field": "amount"
          },
          "y2": {
            "scale": "yscale",
            "value": 0
          }
        },
        "update": {
          "fill": {
            "value": "steelblue"
          }
        },
        "hover": {
          "fill": {
            "value": "red"
          }
        }
      }
    },
    {
      "type": "text",
      "encode": {
        "enter": {
          "align": {
            "value": "center"
          },
          "baseline": {
            "value": "bottom"
          },
          "fill": {
            "value": "#333"
          }
        },
        "update": {
          "x": {
            "scale": "xscale",
            "signal": "tooltip.category",
            "band": 0.5
          },
          "y": {
            "scale": "yscale",
            "signal": "tooltip.amount",
            "offset": -2
          },
          "text": {
            "signal": "tooltip.amount"
          },
          "fillOpacity": [
            {
              "test": "isNaN(tooltip.amount)",
              "value": 0
            },
            {
              "value": 1
            }
          ]
        }
      }
    }
  ]
}